mongodb_proxy.py
openedx_mongodbproxy-0.3.0.dist-info/METADATA
openedx_mongodbproxy-0.3.0.dist-info/WHEEL
openedx_mongodbproxy-0.3.0.dist-info/top_level.txt
openedx_mongodbproxy-0.3.0.dist-info/RECORD
